<dump>
  <flight_plan security_height="0.4" name="Bebop avoid orange TU Delft Cyberzoo" max_dist_from_home="8" lon0="4.3767874" lat0="51.9906361" ground_alt="0" alt="1.0">
    <header>    #include "subsystems/datalink/datalink.h"
    #include "subsystems/electrical.h"
    #include "subsystems/radio_control.h"
    #include "subsystems/ahrs.h"
    #define NPS_GAZEBO_WORLD "cyberzoo_orange_poles.world"</header>
    <waypoints>
      <waypoint name="HOME" lon="4.376796" lat="51.990631" x="0.60" y="-0.56"/>
      <waypoint y="1.0" x="1.9" name="CLIMB"/>
      <waypoint y="1.0" x="1.9" name="STDBY"/>
      <waypoint y="-1.7" x="0.8" name="TD"/>
      <waypoint y="1.0" x="1.9" name="GOAL"/>
      <waypoint y="1.0" x="1.9" name="TRAJECTORY"/>
      <waypoint name="_CZ1" lon="4.3767729" lat="51.9905836" x="-0.89" y="-5.86"/>
      <waypoint name="_CZ2" lon="4.3767138" lat="51.9906365" x="-5.05" y="-0.05"/>
      <waypoint name="_CZ3" lon="4.376805" lat="51.990680" x="1.12" y="4.91"/>
      <waypoint name="_CZ4" lon="4.3768699" lat="51.9906226" x="5.69" y="-1.39"/>
      <waypoint name="_OZ1" lon="4.376776" lat="51.990594" x="-0.69" y="-4.70"/>
      <waypoint name="_OZ2" lon="4.376733" lat="51.990636" x="-3.73" y="-0.08"/>
      <waypoint name="_OZ3" lon="4.376806" lat="51.990671" x="1.20" y="3.91"/>
      <waypoint name="_OZ4" lon="4.376852" lat="51.990624" x="4.46" y="-1.26"/>
    </waypoints>
    <sectors>
      <sector name="CyberZoo" color="red">
        <corner name="_CZ1"/>
        <corner name="_CZ2"/>
        <corner name="_CZ3"/>
        <corner name="_CZ4"/>
      </sector>
      <sector name="ObstacleZone" color="#FF9922">
        <corner name="_OZ1"/>
        <corner name="_OZ2"/>
        <corner name="_OZ3"/>
        <corner name="_OZ4"/>
      </sector>
    </sectors>
    <exceptions>
      <exception deroute="Land here" cond="((datalink_time > 5) &&
      !(IndexOfBlock('Holding point') > nav_block) &&
      !(nav_block >= IndexOfBlock('Land here')) &&
      (autopilot_in_flight() == true) )"/>
      <exception deroute="Land here" cond="(!InsideCyberZoo(GetPosX(), GetPosY()) &&
      !(IndexOfBlock('Holding point') > nav_block) &&
      !(nav_block >= IndexOfBlock('Land here')) &&
      (autopilot_in_flight() == true) )"/>
      <exception deroute="Land here" cond="((GetPosAlt() > 3.5) &&
      !(IndexOfBlock('Holding point') > nav_block) &&
      !(nav_block >= IndexOfBlock('Land here')) &&
      (autopilot_in_flight() == true) )"/>
      <exception deroute="Landed" cond="((GetPosAlt() > 4.5) &&
      !(IndexOfBlock('Holding point') > nav_block) &&
      (autopilot_in_flight() == true) )"/>
      <exception deroute="Land here" cond="(electrical.bat_low &&
      !(IndexOfBlock('Holding point') > nav_block) &&
      !(nav_block >= IndexOfBlock('Land here')) &&
      (autopilot_in_flight() == true) )"/>
      <exception deroute="Land here" cond="(electrical.bat_critical &&
      !(IndexOfBlock('Holding point') > nav_block) &&
      !(nav_block >= IndexOfBlock('Land here')) &&
      (autopilot_in_flight() == true) )"/>
    </exceptions>
    <blocks>
      <block name="Wait GPS" no="0">
        <call_once fun="NavKillThrottle()" no="0"/>
        <while cond="!GpsFixValid()" no="1"/>
      </block>
      <block name="Geo init" no="1">
        <while cond="LessThan(NavBlockTime(), 2)" no="0"/>
        <call_once fun="NavSetAltitudeReferenceHere()" no="2"/>
      </block>
      <block name="Holding point" no="2">
        <call_once fun="NavKillThrottle()" no="0"/>
        <attitude vmode="throttle" until="FALSE" throttle="0" roll="0" pitch="0" no="1"/>
      </block>
      <block name="Start Engine" key="r" no="3">
        <call_once fun="NavResurrect()" no="0"/>
        <attitude vmode="throttle" until="FALSE" throttle="0" roll="0" pitch="0" no="1"/>
        <call_once fun="NavResurrect()" no="2"/>
      </block>
      <block strip_icon="takeoff.png" strip_button="Takeoff" name="Takeoff" key="t" no="4">
        <exception deroute="Standby" cond="GetPosAlt() > 1.0"/>
        <call_once fun="NavSetWaypointHere(WP_CLIMB)" no="0"/>
        <stay wp="CLIMB" vmode="climb" climb="nav_climb_vspeed" no="1"/>
      </block>
      <block strip_icon="home.png" strip_button="Standby" name="Standby" key="s" no="5">
        <call_once fun="NavSetWaypointHere(WP_STDBY)" no="0"/>
        <stay wp="STDBY" no="1"/>
      </block>
      <block name="StayGoal" no="6">
        <stay wp="GOAL" no="0"/>
      </block>
      <block name="Circle" no="7">
        <circle wp="STDBY" radius="1" no="0"/>
      </block>
      <block strip_icon="land-right.png" strip_button="Land Here" name="Land here" key="l" no="8">
        <call_once fun="NavSetWaypointHere(WP_TD)" no="0"/>
        <go wp="TD" no="1"/>
        <deroute block="Flare" no="2"/>
      </block>
      <block name="Land" no="9">
        <go wp="TD" no="0"/>
        <deroute block="Flare" no="1"/>
      </block>
      <block name="Flare" no="10">
        <exception deroute="Holding point" cond="NavDetectGround()"/>
        <exception deroute="Landed" cond="!nav_is_in_flight()"/>
        <exception deroute="Landed" cond="0.10 > GetPosAlt()"/>
        <call_once fun="NavStartDetectGround()" no="0"/>
        <stay wp="TD" vmode="climb" climb="nav_descend_vspeed" no="1"/>
      </block>
      <block name="Landed" no="11">
        <call_once fun="NavKillThrottle()" no="0"/>
        <attitude vmode="throttle" until="FALSE" throttle="0" roll="0" pitch="0" no="1"/>
      </block>
      <block name="HOME" no="12">
        <home no="0"/>
      </block>
    </blocks>
  </flight_plan>
  <stages>
    <stage block="12" block_name="HOME" stage="0">
      <home no="0"/>
    </stage>
    <stage block="11" block_name="Landed" stage="1">
      <attitude vmode="throttle" until="FALSE" throttle="0" roll="0" pitch="0" no="1"/>
    </stage>
    <stage block="11" block_name="Landed" stage="0">
      <call_once fun="NavKillThrottle()" no="0"/>
    </stage>
    <stage block="10" block_name="Flare" stage="1">
      <stay wp="TD" vmode="climb" climb="nav_descend_vspeed" no="1"/>
    </stage>
    <stage block="10" block_name="Flare" stage="0">
      <call_once fun="NavStartDetectGround()" no="0"/>
    </stage>
    <stage block="9" block_name="Land" stage="1">
      <deroute block="Flare" no="1"/>
    </stage>
    <stage block="9" block_name="Land" stage="0">
      <go wp="TD" no="0"/>
    </stage>
    <stage block="8" block_name="Land here" stage="2">
      <deroute block="Flare" no="2"/>
    </stage>
    <stage block="8" block_name="Land here" stage="1">
      <go wp="TD" no="1"/>
    </stage>
    <stage block="8" block_name="Land here" stage="0">
      <call_once fun="NavSetWaypointHere(WP_TD)" no="0"/>
    </stage>
    <stage block="7" block_name="Circle" stage="0">
      <circle wp="STDBY" radius="1" no="0"/>
    </stage>
    <stage block="6" block_name="StayGoal" stage="0">
      <stay wp="GOAL" no="0"/>
    </stage>
    <stage block="5" block_name="Standby" stage="1">
      <stay wp="STDBY" no="1"/>
    </stage>
    <stage block="5" block_name="Standby" stage="0">
      <call_once fun="NavSetWaypointHere(WP_STDBY)" no="0"/>
    </stage>
    <stage block="4" block_name="Takeoff" stage="1">
      <stay wp="CLIMB" vmode="climb" climb="nav_climb_vspeed" no="1"/>
    </stage>
    <stage block="4" block_name="Takeoff" stage="0">
      <call_once fun="NavSetWaypointHere(WP_CLIMB)" no="0"/>
    </stage>
    <stage block="3" block_name="Start Engine" stage="2">
      <call_once fun="NavResurrect()" no="2"/>
    </stage>
    <stage block="3" block_name="Start Engine" stage="1">
      <attitude vmode="throttle" until="FALSE" throttle="0" roll="0" pitch="0" no="1"/>
    </stage>
    <stage block="3" block_name="Start Engine" stage="0">
      <call_once fun="NavResurrect()" no="0"/>
    </stage>
    <stage block="2" block_name="Holding point" stage="1">
      <attitude vmode="throttle" until="FALSE" throttle="0" roll="0" pitch="0" no="1"/>
    </stage>
    <stage block="2" block_name="Holding point" stage="0">
      <call_once fun="NavKillThrottle()" no="0"/>
    </stage>
    <stage block="1" block_name="Geo init" stage="2">
      <call_once fun="NavSetAltitudeReferenceHere()" no="2"/>
    </stage>
    <stage block="1" block_name="Geo init" stage="0">
      <while cond="LessThan(NavBlockTime(), 2)" no="0"/>
    </stage>
    <stage block="0" block_name="Wait GPS" stage="1">
      <while cond="!GpsFixValid()" no="1"/>
    </stage>
    <stage block="0" block_name="Wait GPS" stage="0">
      <call_once fun="NavKillThrottle()" no="0"/>
    </stage>
  </stages>
</dump>
